qpsk_demod/__init__.py
qpsk_demod/main.py
qpsk_demod-0.1.0.dist-info/METADATA
qpsk_demod-0.1.0.dist-info/WHEEL
qpsk_demod-0.1.0.dist-info/top_level.txt
qpsk_demod-0.1.0.dist-info/RECORD
